Workbook
Name Driver: #REF!

Sheet Shipments
A1: SenCol Incorporated | D1: Shipment Analysis | H1: =NOW() -> 46142.761
A3: Product | B3: 2015 | C3: 2015 | D3: 2015 | E3: % | F3: Sell | G3: Gross | H3: Adjusted | I3: Gross | J3: Gross | K3: Profit | L3: Contribution | M3: Quality | N3: 2016 | O3: % Change
A4: Name | B4: QTY Shipped | C4: Rejects | D4: Net | E4: Rejects | F4: Price | G4: Revenue | H4: Revenue | I4: COGS | J4: Profit | K4: Margin | L4: Award | M4: Bonus | N4: QTY | O4: 2015-2016
A5: Fixo | B5: 910000 | C5: 29000 | D5: =B5-C5 -> 881000 | E5: =C5/B5 -> 0.031868132 | F5: 145 | G5: =D5*F5 -> 127745000 | H5: =G5-C5*(F5+0.75) -> 123518250 | I5: 26200000 | J5: =H5-I5 -> 97318250 | K5: =(H5-I5)/G5 -> 0.76181651 | L5: =IF(K5>=75%,"YES",".") -> YES | M5: =IF(E5<5%,1800000,750000) -> 1800000 | N5: 791065 | O5: =(N5-D5)/D5 -> -0.10208286
A6: Galbar | B6: 1145000 | C6: 86400 | D6: =B6-C6 -> 1058600 | E6: =C6/B6 -> 0.075458515 | F6: 170 | G6: =D6*F6 -> 179962000 | H6: =G6-C6*(F6+0.75) -> 165209200 | I6: 54870900 | J6: =H6-I6 -> 110338300 | K6: =(H6-I6)/G6 -> 0.61311999 | L6: =IF(K6>=75%,"YES",".") -> . | M6: =IF(E6<5%,1800000,750000) -> 750000 | N6: 1127409 | O6: =(N6-D6)/D6 -> 0.065
A7: Wexit | B7: 642700 | C7: 13950 | D7: =B7-C7 -> 628750 | E7: =C7/B7 -> 0.021705306 | F7: 210 | G7: =D7*F7 -> 132037500 | H7: =G7-C7*(F7+0.75) -> 1.2909754e+08 | I7: 26890700 | J7: =H7-I7 -> 1.0220684e+08 | K7: =(H7-I7)/G7 -> 0.77407432 | L7: =IF(K7>=75%,"YES",".") -> YES | M7: =IF(E7<5%,1800000,750000) -> 1800000 | N7: 540725 | O7: =(N7-D7)/D7 -> -0.14
A8: Trufir | B8: 490680 | C8: 9540 | D8: =B8-C8 -> 481140 | E8: =C8/B8 -> 0.019442406 | F8: 98 | G8: =D8*F8 -> 47151720 | H8: =G8-C8*(F8+0.75) -> 46209645 | I8: 11245780 | J8: =H8-I8 -> 34963865 | K8: =(H8-I8)/G8 -> 0.74151834 | L8: =IF(K8>=75%,"YES",".") -> . | M8: =IF(E8<5%,1800000,750000) -> 1800000 | N8: 492206 | O8: =(N8-D8)/D8 -> 0.022999543
A9: Oxtin | B9: 998860 | C9: 54860 | D9: =B9-C9 -> 944000 | E9: =C9/B9 -> 0.054922612 | F9: 125 | G9: =D9*F9 -> 118000000 | H9: =G9-C9*(F9+0.75) -> 111101355 | I9: 39670900 | J9: =H9-I9 -> 71430455 | K9: =(H9-I9)/G9 -> 0.60534284 | L9: =IF(K9>=75%,"YES",".") -> . | M9: =IF(E9<5%,1800000,750000) -> 750000 | N9: 900576 | O9: =(N9-D9)/D9 -> -0.046
A11: Total | B11: =SUM(B5:B9) -> 4187240 | C11: =SUM(C5:C9) -> 193750 | D11: =SUM(D5:D9) -> 3993490 | E11: =C11/B11 -> 0.04627153 | G11: =SUM(G5:G9) -> 604896220 | H11: =SUM(H5:H9) -> 5.7513599e+08 | I11: =SUM(I5:I9) -> 158878280 | J11: =SUM(J5:J9) -> 4.1625771e+08 | K11: =(H11-I11)/G11 -> 0.68814731 | M11: =SUM(M5:M9) -> 6900000 | N11: =SUM(N5:N9) -> 3851981 | O11: =(N11-D11)/D11 -> -0.03543492
A12: Average | B12: =AVERAGE(B5:B9) -> 837448 | C12: =AVERAGE(C5:C9) -> 38750 | D12: =AVERAGE(D5:D9) -> 798698 | E12: =AVERAGE(E5:E9) -> 0.040679394 | F12: =AVERAGE(F5:F9) -> 149.6 | G12: =AVERAGE(G5:G9) -> 120979244 | H12: =AVERAGE(H5:H9) -> 1.150272e+08 | I12: =AVERAGE(I5:I9) -> 31775656 | ... K12: =AVERAGE(K5:K9) -> 0.6991744 | M12: =AVERAGE(M5:M9) -> 1380000 | N12: =AVERAGE(N5:N9) -> 770396.2 | O12: =AVERAGE(O5:O9) -> -0.040016664

Sheet Forecast
A1: =Shipments!A1 -> SenCol Incorporated | E1: Shipping Forecast | H1: =TODAY() -> 46142
A3: =Shipments!A3 -> Product | B3: =Shipments!D3 -> 2015 | C3: =Shipments!N3 -> 2016 | D3: =Shipments!F3 -> Sell | E3: 2017 | F3: 2017 | G3: 2018 | H3: 2018 | I3: 2018 | J3: 2019 | K3: % Change | L3: 2019 | N3: Policy Table
A4: =Shipments!A4 -> Name | B4: =Shipments!D4 -> Net | C4: =Shipments!N4 -> QTY | D4: =Shipments!F4 -> Price | E4: QTY | F4: Rating | G4: QTY | H4: Allowance | I4: Rating | J4: QTY | K4: 2015-2019 | L4: Allowance | N4: Rating | O4: QTY | P4: Allowance
A5: =Shipments!A5 -> Fixo | B5: =Shipments!D5 -> 881000 | C5: =Shipments!N5 -> 791065 | D5: =Shipments!F5 -> 145 | E5: =C5-C5*4% -> 759422.4 | F5: 3 | G5: =IF(F5>=4,E5*1.055,E5*1.015) -> 770813.74 | H5: =IF(F5<3,1500000,1000000) -> 1000000 | I5: 4 | J5: =VLOOKUP(I5,$N$5:$P$9,2)*G5+G5 -> 819375 | K5: =(J5-B5)/B5 -> -0.06994892 | L5: =VLOOKUP(I5,$N$5:$P$9,3)*J5+125000 -> 2091500 | N5: 1 | O5: 0.005 | P5: 0.75
A6: =Shipments!A6 -> Galbar | B6: =Shipments!D6 -> 1058600 | C6: =Shipments!N6 -> 1127409 | D6: =Shipments!F6 -> 170 | E6: =C6-C6*4% -> 1082312.6 | F6: 2 | G6: =IF(F6>=4,E6*1.055,E6*1.015) -> 1098547.3 | H6: =IF(F6<3,1500000,1000000) -> 1500000 | I6: 5 | J6: =VLOOKUP(I6,$N$5:$P$9,2)*G6+G6 -> 1180938.4 | K6: =(J6-B6)/B6 -> 0.1155662 | L6: =VLOOKUP(I6,$N$5:$P$9,3)*J6+125000 -> 3667815.1 | N6: 2 | O6: 0.014 | P6: 1.15
A7: =Shipments!A7 -> Wexit | B7: =Shipments!D7 -> 628750 | C7: =Shipments!N7 -> 540725 | D7: =Shipments!F7 -> 210 | E7: =C7-C7*4% -> 519096 | F7: 5 | G7: =IF(F7>=4,E7*1.055,E7*1.015) -> 547646.28 | H7: =IF(F7<3,1500000,1000000) -> 1000000 | I7: 3 | J7: =VLOOKUP(I7,$N$5:$P$9,2)*G7+G7 -> 562980.38 | K7: =(J7-B7)/B7 -> -0.10460378 | L7: =VLOOKUP(I7,$N$5:$P$9,3)*J7+125000 -> 1138364.7 | N7: 3 | O7: 0.028 | P7: 1.8
A8: =Shipments!A8 -> Trufir | B8: =Shipments!D8 -> 481140 | C8: =Shipments!N8 -> 492206 | D8: =Shipments!F8 -> 98 | E8: =C8-C8*4% -> 472517.76 | F8: 4 | G8: =IF(F8>=4,E8*1.055,E8*1.015) -> 498506.24 | H8: =IF(F8<3,1500000,1000000) -> 1000000 | I8: 4 | J8: =VLOOKUP(I8,$N$5:$P$9,2)*G8+G8 -> 529912.13 | K8: =(J8-B8)/B8 -> 0.10136785 | L8: =VLOOKUP(I8,$N$5:$P$9,3)*J8+125000 -> 1396789.1 | N8: 4 | O8: 0.063 | P8: 2.4
A9: =Shipments!A9 -> Oxtin | B9: =Shipments!D9 -> 944000 | C9: =Shipments!N9 -> 900576 | D9: =Shipments!F9 -> 125 | E9: =C9-C9*4% -> 864552.96 | F9: 3 | G9: =IF(F9>=4,E9*1.055,E9*1.015) -> 877521.25 | H9: =IF(F9<3,1500000,1000000) -> 1000000 | I9: 3 | J9: =VLOOKUP(I9,$N$5:$P$9,2)*G9+G9 -> 902091.85 | K9: =(J9-B9)/B9 -> -0.044394227 | L9: =VLOOKUP(I9,$N$5:$P$9,3)*J9+125000 -> 1748765.3 | N9: 5 | O9: 0.075 | P9: 3

Sheet Freight
A1: =Forecast!A1 -> SenCol Incorporated | E1: Freight Analysis | I1: =NOW() -> 46142.761
A3: =Forecast!A3 -> Product | B3: Customer | C3: =Forecast!J3 -> 2019 | D3: 2019 | E3: WPU | F3: UPC | G3: CPP | H3: Product | I3: Total | J3: Total | K3: Truck | L3: Gross | M3: Truck | N3: Transit | O3: Freight | P3: Accessorials | Q3: Total Freight | R3: FCPR | S3: FCPU
A4: =Forecast!A4 -> Name | B4: Score | C4: =Forecast!J4 -> QTY | D4: Revenue | E4: Net | F4: Net | G4: Net | H4: Weight | I4: Cartons | J4: Pallets | K4: Number | L4: Weight | M4: Trips | N4: KM | O4: Cost | P4: Cost | Q4: Cost
A5: =Forecast!A5 -> Fixo | B5: 4 | C5: =Forecast!J5 -> 819375 | D5: 126183750 | E5: 2.5 | F5: 10 | G5: 9 | H5: =C5*E5 -> 2048437.5 | I5: =C5/F5 -> 81937.5 | J5: =I5/G5 -> 9104.1667 | K5: 4000 | L5: =H5+(I5*4)+(J5*22) -> 2576479.2 | M5: =ROUNDUP((L5/5000),0) -> 516 | N5: 43344 | O5: =(VLOOKUP(K5,$O$13:$R$18,2,FALSE))*L5 -> 721414.17 | P5: =((VLOOKUP(K5,$O$13:$R$18,3,FALSE))*D5)+(VLOOKUP(K5,$O$13:$R$18,4,FALSE)*N5) -> 513837.24 | Q5: =SUM(O5:P5) -> 1235251.4 | R5: =Q5/D5 -> 0.0097893065 | S5: =Q5/C5 -> 1.5075532
A6: =Forecast!A6 -> Galbar | B6: 3 | C6: =Forecast!J6 -> 1180938.4 | D6: 224378292 | E6: 1.3 | F6: 15 | G6: 14 | H6: =C6*E6 -> 1535219.9 | I6: =C6/F6 -> 78729.225 | J6: =I6/G6 -> 5623.5161 | K6: 1800 | L6: =H6+(I6*4)+(J6*22) -> 1973854.1 | M6: =ROUNDUP((L6/5000),0) -> 395 | N6: 37525 | O6: =(VLOOKUP(K6,$O$13:$R$18,2,FALSE))*L6 -> 769803.12 | P6: =((VLOOKUP(K6,$O$13:$R$18,3,FALSE))*D6)+(VLOOKUP(K6,$O$13:$R$18,4,FALSE)*N6) -> 1351898.5 | Q6: =SUM(O6:P6) -> 2121701.6 | R6: =Q6/D6 -> 0.0094559131 | S6: =Q6/C6 -> 1.7966235
A7: =Forecast!A7 -> Wexit | B7: 3 | C7: =Forecast!J7 -> 562980.38 | D7: 135115290 | E7: 2 | F7: 18 | G7: 18 | H7: =C7*E7 -> 1125960.8 | I7: =C7/F7 -> 31276.688 | J7: =I7/G7 -> 1737.5938 | K7: 2500 | L7: =H7+(I7*4)+(J7*22) -> 1289294.6 | M7: =ROUNDUP((L7/5000),0) -> 258 | N7: 11094 | O7: =(VLOOKUP(K7,$O$13:$R$18,2,FALSE))*L7 -> 528610.77 | P7: =((VLOOKUP(K7,$O$13:$R$18,3,FALSE))*D7)+(VLOOKUP(K7,$O$13:$R$18,4,FALSE)*N7) -> 812688.66 | Q7: =SUM(O7:P7) -> 1341299.4 | R7: =Q7/D7 -> 0.0099270736 | S7: =Q7/C7 -> 2.3824977
A8: =Forecast!A8 -> Trufir | B8: 2 | C8: =Forecast!J8 -> 529912.13 | D8: 47692092 | E8: 3.1 | F8: 6 | G8: 4 | H8: =C8*E8 -> 1642727.6 | I8: =C8/F8 -> 88318.688 | J8: =I8/G8 -> 22079.672 | K8: 4900 | L8: =H8+(I8*4)+(J8*22) -> 2481755.1 | M8: =ROUNDUP((L8/5000),0) -> 497 | N8: 43239 | O8: =(VLOOKUP(K8,$O$13:$R$18,2,FALSE))*L8 -> 1613140.8 | P8: =((VLOOKUP(K8,$O$13:$R$18,3,FALSE))*D8)+(VLOOKUP(K8,$O$13:$R$18,4,FALSE)*N8) -> 468640.91 | Q8: =SUM(O8:P8) -> 2081781.8 | R8: =Q8/D8 -> 0.04365046 | S8: =Q8/C8 -> 3.9285414
A9: =Forecast!A9 -> Oxtin | B9: 3 | C9: =Forecast!J9 -> 902091.85 | D9: 89307093 | E9: 1.6 | F9: 20 | G9: 9 | H9: =C9*E9 -> 1443347 | I9: =C9/F9 -> 45104.592 | J9: =I9/G9 -> 5011.6214 | K9: 5800 | L9: =H9+(I9*4)+(J9*22) -> 1734021 | M9: =ROUNDUP((L9/5000),0) -> 347 | N9: 14227 | O9: =(VLOOKUP(K9,$O$13:$R$18,2,FALSE))*L9 -> 606907.35 | P9: =((VLOOKUP(K9,$O$13:$R$18,3,FALSE))*D9)+(VLOOKUP(K9,$O$13:$R$18,4,FALSE)*N9) -> 537976.61 | Q9: =SUM(O9:P9) -> 1144884 | R9: =Q9/D9 -> 0.012819631 | S9: =Q9/C9 -> 1.2691434
A12: Highest 2019 Qty | D12: =MAX(C5:C9) -> 1180938.4 | F12: Number of Products with less than 25,000 Transit KM | K12: =COUNTIF(N5:N9,"<25000") -> 2 | O12: Rate Table
O13: Truck | P13: $ Per Lb | Q13: Insurance | R13: Maintainance
A14: Lowest 2019 QTY | D14: =MIN(C5:C9) -> 529912.13 | F14: Total 2019 Revenue that is in in excess of $100M | K14: =SUMIF(D5:D9, ">100000000") -> 485677332 | O14: 1800 | P14: 0.39 | Q14: 0.006 | R14: 0.15
O15: 2500 | P15: 0.41 | Q15: 0.006 | R15: 0.18
A16: 2nd Highest Total Cartons | D16: =LARGE(I5:I9,2) -> 81937.5 | F16: Most common Customer Score | K16: =MODE(B5:B9) -> 3 | O16: 4000 | P16: 0.28 | Q16: 0.004 | R16: 0.21
O17: 4900 | P17: 0.65 | Q17: 0.0095 | R17: 0.36
A18: 3rd Lowest Total Cartons | D18: =SMALL(I5:I9,3) -> 78729.225 | F18: Median Truck Trips | K18: =MEDIAN(M5:M9) -> 395 | O18: 5800 | P18: 0.35 | Q18: 0.006 | R18: 0.15
A20: Overall Freight Cost as % of Revenue | D20: =AVERAGE(Q5:Q9)/AVERAGE(D5:D9) -> 0.012727183 | F20: Projected Total Freight Cost if we add a 15% surcharge | K20: =SUM(Q5:Q9)*1.15 -> 9113655.9
